Workbook

Sheet Summary
A1: SIRI E-Learning Platform — Requirements Summary
A3: Category | B3: Must-Have | C3: Nice-to-Have | D3: Total
A4: Learner Experience | B4: =COUNTIFS('Platform Requirements'!$A$2:$A$41,$A4,'Platform Requirements'!$D$2:$D$41,B$3) -> 6 | C4: =COUNTIFS('Platform Requirements'!$A$2:$A$41,$A4,'Platform Requirements'!$D$2:$D$41,C$3) -> 9 | D4: =SUM(B4:C4) -> 15
A5: Instructor Dashboard | B5: =COUNTIFS('Platform Requirements'!$A$2:$A$41,$A5,'Platform Requirements'!$D$2:$D$41,B$3) -> 1 | C5: =COUNTIFS('Platform Requirements'!$A$2:$A$41,$A5,'Platform Requirements'!$D$2:$D$41,C$3) -> 2 | D5: =SUM(B5:C5) -> 3
A6: Admin & Management | B6: =COUNTIFS('Platform Requirements'!$A$2:$A$41,$A6,'Platform Requirements'!$D$2:$D$41,B$3) -> 2 | C6: =COUNTIFS('Platform Requirements'!$A$2:$A$41,$A6,'Platform Requirements'!$D$2:$D$41,C$3) -> 1 | D6: =SUM(B6:C6) -> 3
A7: Security & Anti-Piracy | B7: =COUNTIFS('Platform Requirements'!$A$2:$A$41,$A7,'Platform Requirements'!$D$2:$D$41,B$3) -> 3 | C7: =COUNTIFS('Platform Requirements'!$A$2:$A$41,$A7,'Platform Requirements'!$D$2:$D$41,C$3) -> 0 | D7: =SUM(B7:C7) -> 3
A8: Account & Access | B8: =COUNTIFS('Platform Requirements'!$A$2:$A$41,$A8,'Platform Requirements'!$D$2:$D$41,B$3) -> 2 | C8: =COUNTIFS('Platform Requirements'!$A$2:$A$41,$A8,'Platform Requirements'!$D$2:$D$41,C$3) -> 0 | D8: =SUM(B8:C8) -> 2
A9: AI & Personalization | B9: =COUNTIFS('Platform Requirements'!$A$2:$A$41,$A9,'Platform Requirements'!$D$2:$D$41,B$3) -> 0 | C9: =COUNTIFS('Platform Requirements'!$A$2:$A$41,$A9,'Platform Requirements'!$D$2:$D$41,C$3) -> 4 | D9: =SUM(B9:C9) -> 4
A10: Payment & Finance | B10: =COUNTIFS('Platform Requirements'!$A$2:$A$41,$A10,'Platform Requirements'!$D$2:$D$41,B$3) -> 3 | C10: =COUNTIFS('Platform Requirements'!$A$2:$A$41,$A10,'Platform Requirements'!$D$2:$D$41,C$3) -> 1 | D10: =SUM(B10:C10) -> 4
A11: Business Model | B11: =COUNTIFS('Platform Requirements'!$A$2:$A$41,$A11,'Platform Requirements'!$D$2:$D$41,B$3) -> 0 | C11: =COUNTIFS('Platform Requirements'!$A$2:$A$41,$A11,'Platform Requirements'!$D$2:$D$41,C$3) -> 2 | D11: =SUM(B11:C11) -> 2
A12: Compliance & Non-Functional | B12: =COUNTIFS('Platform Requirements'!$A$2:$A$41,$A12,'Platform Requirements'!$D$2:$D$41,B$3) -> 4 | C12: =COUNTIFS('Platform Requirements'!$A$2:$A$41,$A12,'Platform Requirements'!$D$2:$D$41,C$3) -> 0 | D12: =SUM(B12:C12) -> 4
A13: Total | B13: =SUM(B4:B12) -> 21 | C13: =SUM(C4:C12) -> 19 | D13: =SUM(D4:D12) -> 40
A16: Development Phase | B16: Items
A17: MVP | B17: =COUNTIF('Platform Requirements'!$E$2:$E$41,A17) -> 21
A18: Phase 2 | B18: =COUNTIF('Platform Requirements'!$E$2:$E$41,A18) -> 19
A19: Total | B19: =SUM(B17:B18) -> 40

Sheet Platform Requirements
A1: Category | B1: Feature / Topic | C1: Description | D1: Priority / Type | E1: Phase
A2: Learner Experience | B2: Smart Search & Deep Categorization | C2: Search system with filters (category, difficulty, price, rating) and Mega Menu for easy navigation. | D2: Must-Have | E2: =IF($D2="Must-Have","MVP","Phase 2") -> MVP
A3: Learner Experience | B3: Course Detail & Syllabus Preview | C3: Clear course structure showing episodes, duration, free previews, and learning outcomes. | D3: Must-Have | E3: =IF($D3="Must-Have","MVP","Phase 2") -> MVP
A4: Learner Experience | B4: Advanced Video Player | C4: Netflix-like player: adjustable speed (0.5x-2.0x), resume playback, and auto-resolution based on bandwidth. | D4: Must-Have | E4: =IF($D4="Must-Have","MVP","Phase 2") -> MVP
A5: Learner Experience | B5: Interactive Learning per Episode | C5: Support for various content types per episode: video, attachments (PDF/Code), end-of-lesson quizzes, and assignments. | D5: Must-Have | E5: =IF($D5="Must-Have","MVP","Phase 2") -> MVP
A6: Learner Experience | B6: Progress Tracking & Gamification | C6: Visual progress bar and automated Certificate of Completion upon finishing the course. | D6: Nice-to-Have | E6: =IF($D6="Must-Have","MVP","Phase 2") -> Phase 2
A7: Learner Experience | B7: Seamless Checkout & Payment | C7: Support multiple payment methods: QR PromptPay, Credit Card, and Installments for high-ticket courses. | D7: Must-Have | E7: =IF($D7="Must-Have","MVP","Phase 2") -> MVP
A8: Learner Experience | B8: Q&A & Community | C8: Discussion board or comment section under each episode for direct interaction with instructors. | D8: Nice-to-Have | E8: =IF($D8="Must-Have","MVP","Phase 2") -> Phase 2
A9: Learner Experience | B9: Review & Rating System | C9: Learners rate and review courses after enrollment; ratings feed search filters and build course credibility. (Benchmark: Udemy) | D9: Must-Have | E9: =IF($D9="Must-Have","MVP","Phase 2") -> MVP
A10: Learner Experience | B10: Wishlist & Shopping Cart | C10: Save courses for later and purchase multiple courses in a single checkout. (Benchmark: Udemy) | D10: Nice-to-Have | E10: =IF($D10="Must-Have","MVP","Phase 2") -> Phase 2
A11: Learner Experience | B11: Learner Notification System | C11: Email / LINE / push notifications for new lessons, promotions, and learning reminders to reduce drop-off. | D11: Nice-to-Have | E11: =IF($D11="Must-Have","MVP","Phase 2") -> Phase 2
A12: Learner Experience | B12: Multi-language Subtitles | C12: Thai/English subtitles and closed captions on course videos. (Benchmark: Udemy) | D12: Nice-to-Have | E12: =IF($D12="Must-Have","MVP","Phase 2") -> Phase 2
A13: Learner Experience | B13: Offline Download (Mobile App) | C13: Download lessons for offline viewing in the mobile app with DRM protection. (Benchmark: Udemy) | D13: Nice-to-Have | E13: =IF($D13="Must-Have","MVP","Phase 2") -> Phase 2
... A41: Compliance & Non-Functional | B41: Backup & Disaster Recovery | C41: Automated daily backups and documented recovery plan (RTO/RPO). | D41: Must-Have | E41: =IF($D41="Must-Have","MVP","Phase 2") -> MVP

Sheet Branding Options
A1: Focus Group | B1: Name Candidates
A2: Skill & Improvement Focus | B2: SiriSkill, Siri UpSkill, Siri Forward, Siri Mastery
A3: Academy & Education Focus | B3: Siri Academy, Siri Campus, SiriLearn, Siri EdSpace
A4: Catchy & Modern Focus | B4: Siri Class, Siri Hub, Siri X, Siri Brain
A5: Premium & Exclusive Focus | B5: Siri Masterclass, Siri Elite
